flask_gcm/__init__.py
flask_gcm/test/__init__.py
flask_gcm/test/conftest.py
flask_gcm/test/test_flask_gcm.py
Flask_GCM-0.2.1.dist-info/LICENSE
Flask_GCM-0.2.1.dist-info/METADATA
Flask_GCM-0.2.1.dist-info/WHEEL
Flask_GCM-0.2.1.dist-info/entry_points.txt
Flask_GCM-0.2.1.dist-info/top_level.txt
Flask_GCM-0.2.1.dist-info/RECORD
