Metadata-Version: 2.1
Name: Flask-GCM
Version: 0.2.1
Summary: Flask-GCM is a simple wrapper for the python-gcm library to be used with Flask applications.
Home-page: https://github.com/michiganlabs/flask-gcm
Author: Josh Friend
Author-email: jfriend@michiganlabs.com
License: MIT
Platform: UNKNOWN
Classifier: Development Status :: 3 - Alpha
Classifier: Natural Language :: English
Classifier: Operating System :: OS Independent
Classifier: License :: OSI Approved :: MIT License
Classifier: Programming Language :: Python :: 2.6
Classifier: Programming Language :: Python :: 2.7
Requires-Dist: gcm-client (==0.1.4)
Requires-Dist: Flask
